_fadvise.c
setup.py
fadvise/__init__.py
fadvise.egg-info/PKG-INFO
fadvise.egg-info/SOURCES.txt
fadvise.egg-info/dependency_links.txt
fadvise.egg-info/top_level.txt