Metadata-Version: 1.0
Name: fadvise
Version: 6.0.0
Summary: Python interface to posix_fadvise(2)
Home-page: https://chris-lamb.co.uk/projects/python-fadvise
Author: Chris Lamb
Author-email: chris@chris-lamb.co.uk
License: BSD
Platform: UNKNOWN
